[{
    "duration_bin": 5700,
    "games_played": 1,
    "wins": 1
}, {
    "duration_bin": 3300,
    "games_played": 218,
    "wins": 92
}, {
    "duration_bin": 1800,
    "games_played": 2652,
    "wins": 1308
}, {
    "duration_bin": 3900,
    "games_played": 43,
    "wins": 26
}, {
    "duration_bin": 300,
    "games_played": 14,
    "wins": 8
}, {
    "duration_bin": 6000,
    "games_played": 2,
    "wins": 0
}, {
    "duration_bin": 3000,
    "games_played": 512,
    "wins": 243
}, {
    "duration_bin": 4200,
    "games_played": 24,
    "wins": 10
}, {
    "duration_bin": 4500,
    "games_played": 11,
    "wins": 7
}, {
    "duration_bin": 1200,
    "games_played": 1381,
    "wins": 736
}, {
    "duration_bin": 2700,
    "games_played": 761,
    "wins": 383
}, {
    "duration_bin": 5100,
    "games_played": 2,
    "wins": 0
}, {
    "duration_bin": 2100,
    "games_played": 1967,
    "wins": 966
}, {
    "duration_bin": 5400,
    "games_played": 1,
    "wins": 0
}, {
    "duration_bin": 900,
    "games_played": 407,
    "wins": 191
}, {
    "duration_bin": 600,
    "games_played": 96,
    "wins": 51
}, {
    "duration_bin": 2400,
    "games_played": 1503,
    "wins": 770
}, {
    "duration_bin": 3600,
    "games_played": 119,
    "wins": 54
}, {
    "duration_bin": 1500,
    "games_played": 2140,
    "wins": 1067
}, {
    "duration_bin": 4800,
    "games_played": 3,
    "wins": 1
}]